nonebot_plugin_bard_bot/__init__.py
nonebot_plugin_bard_bot/config.py
nonebot_plugin_bard_bot-0.1.8.dist-info/LICENSE
nonebot_plugin_bard_bot-0.1.8.dist-info/METADATA
nonebot_plugin_bard_bot-0.1.8.dist-info/WHEEL
nonebot_plugin_bard_bot-0.1.8.dist-info/RECORD
