Metadata-Version: 2.1
Name: nonebot-plugin-bard-bot
Version: 0.1.8
Summary: 一个非常简单但是很可用的使得在QQ中可以使用Google Bard的插件
License: MIT
Author: leafdeveloper
Requires-Python: >=3.8
Classifier: License :: OSI Approved :: MIT License
Classifier: Programming Language :: Python :: 3
Classifier: Programming Language :: Python :: 3.8
Classifier: Programming Language :: Python :: 3.9
Classifier: Programming Language :: Python :: 3.10
Classifier: Programming Language :: Python :: 3.11
